claude_tools/__init__.py
claude_tools/calculator.py
claude_tools/datetime_tool.py
claude_tools/main.py
claude_tools/weather.py
mseep_claude_tools-0.1.4.dist-info/licenses/LICENSE
mseep_claude_tools-0.1.4.dist-info/METADATA
mseep_claude_tools-0.1.4.dist-info/WHEEL
mseep_claude_tools-0.1.4.dist-info/entry_points.txt
mseep_claude_tools-0.1.4.dist-info/top_level.txt
mseep_claude_tools-0.1.4.dist-info/RECORD
